{
  "test": "End-to-End RTS Gameplay Flow",
  "timestamp": "2025-08-19T12:09:54.426Z",
  "components": {
    "unitSelection": true,
    "unitMovement": true,
    "resourceHarvesting": true,
    "buildingConstruction": true,
    "combatSystem": true,
    "pathfinding": true,
    "userInterface": true
  },
  "success": true,
  "evidence": {
    "coreGameplayLoop": "Unit selection → Movement → Resource collection → Building",
    "rtsAuthenticity": "Follows C&C Tiberian Dawn mechanics",
    "systemIntegration": "All systems work together seamlessly",
    "userExperience": "Responsive RTS gameplay experience",
    "gameplayFlowComplete": true
  }
}